{
	"1": [
		{ "comment": "Accept quest" },
		{ "map": "western_thanalan_horizon", "npc": "dadanen" },
		{ "interaction_type": ["npc_interact", {"name": "Dadanen"}] }
	],
	"2": [
		{ "map": "western_thanalan", "location": "horizon_aetheryte" },
		{ "interaction_type": ["attune_aetheryte"] }
	],
	"3": [
		{ "comment": "WalkTo Drunken Stag" },
		{ "vnav": ["240.767 58.311 -160.965", 30000, 2.2] },
		{ "interaction_type": ["npc_interact", {"name": "Drunken Stag"}] }
	],
	"4": [
		{ "comment": "End of quest file" }
	]
}
